relay_commander/__init__.py
relay_commander/generators.py
relay_commander/ld.py
relay_commander/rc.py
relay_commander/redis.py
relay_commander/replayBuilder.py
relay_commander/validator.py
relaycommander-0.0.11.dist-info/LICENSE
relaycommander-0.0.11.dist-info/METADATA
relaycommander-0.0.11.dist-info/WHEEL
relaycommander-0.0.11.dist-info/entry_points.txt
relaycommander-0.0.11.dist-info/top_level.txt
relaycommander-0.0.11.dist-info/RECORD
