Metadata-Version: 2.1
Name: relaycommander
Version: 0.0.11
Summary: CLI to Update LD Relay in Disaster Scenarios
Home-page: https://github.com/launchdarkly/relayCommander
Author: LaunchDarkly
Author-email: sales@launchdarkly.com
License: Apache 2.0
Keywords: launchdarkly api redis relay
Platform: UNKNOWN
Classifier: Development Status :: 3 - Alpha
Classifier: Intended Audience :: Developers
Classifier: Intended Audience :: System Administrators
Classifier: License :: OSI Approved :: Apache Software License
Classifier: Operating System :: OS Independent
Classifier: Topic :: System :: Recovery Tools
Classifier: Topic :: System :: Systems Administration
Classifier: Programming Language :: Python :: 3 :: Only
Requires-Python: ~=3.5
Requires-Dist: click
Requires-Dist: click-log
Requires-Dist: requests
Requires-Dist: redis
Requires-Dist: jinja2
Requires-Dist: launchdarkly-api
